pathtree/__init__.py
pathtree/__main__.py
pathtree/pathtree.py
pathtree.husky-0.0.9.dist-info/LICENSE
pathtree.husky-0.0.9.dist-info/METADATA
pathtree.husky-0.0.9.dist-info/WHEEL
pathtree.husky-0.0.9.dist-info/entry_points.txt
pathtree.husky-0.0.9.dist-info/top_level.txt
pathtree.husky-0.0.9.dist-info/RECORD
