Metadata-Version: 2.1
Name: pathtree.husky
Version: 0.0.9
Summary: pathtree implements a tree for fast path lookup.
Home-page: https://github.com/zsysuper/pathtree
Author: husky
Author-email: 215941106@qq.com
License: BSD
Keywords: pathtree
Platform: UNKNOWN
Classifier: Development Status :: 4 - Beta
Classifier: Intended Audience :: Developers
Classifier: License :: OSI Approved :: BSD License
Classifier: Operating System :: OS Independent
Classifier: Programming Language :: Python
Classifier: Topic :: System :: Distributed Computing
